{
	"configurations" : 
	[
		{
			"directories" : 
			[
				{
					"build" : ".",
					"minimumCMakeVersion" : 
					{
						"string" : "3.0.0"
					},
					"projectIndex" : 0,
					"source" : ".",
					"targetIndexes" : 
					[
						0,
						1,
						2,
						3,
						4,
						5,
						6
					]
				}
			],
			"name" : "Debug",
			"projects" : 
			[
				{
					"directoryIndexes" : 
					[
						0
					],
					"name" : "c_bsearch",
					"targetIndexes" : 
					[
						0,
						1,
						2,
						3,
						4,
						5,
						6
					]
				}
			],
			"targets" : 
			[
				{
					"directoryIndex" : 0,
					"id" : "ALL_BUILD::@6890427a1f51a3e7e1df",
					"jsonFile" : "target-ALL_BUILD-Debug-5b245edb474940f28915.json",
					"name" : "ALL_BUILD",
					"projectIndex" : 0
				},
				{
					"directoryIndex" : 0,
					"id" : "Continuous::@6890427a1f51a3e7e1df",
					"jsonFile" : "target-Continuous-Debug-6937c282c87d83acf1d2.json",
					"name" : "Continuous",
					"projectIndex" : 0
				},
				{
					"directoryIndex" : 0,
					"id" : "Experimental::@6890427a1f51a3e7e1df",
					"jsonFile" : "target-Experimental-Debug-dc6bf66df4253e53347b.json",
					"name" : "Experimental",
					"projectIndex" : 0
				},
				{
					"directoryIndex" : 0,
					"id" : "Nightly::@6890427a1f51a3e7e1df",
					"jsonFile" : "target-Nightly-Debug-0a1b71b900fba136c7a2.json",
					"name" : "Nightly",
					"projectIndex" : 0
				},
				{
					"directoryIndex" : 0,
					"id" : "NightlyMemoryCheck::@6890427a1f51a3e7e1df",
					"jsonFile" : "target-NightlyMemoryCheck-Debug-ee307b85b0f4c82b359b.json",
					"name" : "NightlyMemoryCheck",
					"projectIndex" : 0
				},
				{
					"directoryIndex" : 0,
					"id" : "ZERO_CHECK::@6890427a1f51a3e7e1df",
					"jsonFile" : "target-ZERO_CHECK-Debug-86bbd08886eff00bd66f.json",
					"name" : "ZERO_CHECK",
					"projectIndex" : 0
				},
				{
					"directoryIndex" : 0,
					"id" : "c_bsearch::@6890427a1f51a3e7e1df",
					"jsonFile" : "target-c_bsearch-Debug-4f92d2d688a5926f86d2.json",
					"name" : "c_bsearch",
					"projectIndex" : 0
				}
			]
		},
		{
			"directories" : 
			[
				{
					"build" : ".",
					"minimumCMakeVersion" : 
					{
						"string" : "3.0.0"
					},
					"projectIndex" : 0,
					"source" : ".",
					"targetIndexes" : 
					[
						0,
						1,
						2,
						3,
						4,
						5,
						6
					]
				}
			],
			"name" : "Release",
			"projects" : 
			[
				{
					"directoryIndexes" : 
					[
						0
					],
					"name" : "c_bsearch",
					"targetIndexes" : 
					[
						0,
						1,
						2,
						3,
						4,
						5,
						6
					]
				}
			],
			"targets" : 
			[
				{
					"directoryIndex" : 0,
					"id" : "ALL_BUILD::@6890427a1f51a3e7e1df",
					"jsonFile" : "target-ALL_BUILD-Release-5b245edb474940f28915.json",
					"name" : "ALL_BUILD",
					"projectIndex" : 0
				},
				{
					"directoryIndex" : 0,
					"id" : "Continuous::@6890427a1f51a3e7e1df",
					"jsonFile" : "target-Continuous-Release-6937c282c87d83acf1d2.json",
					"name" : "Continuous",
					"projectIndex" : 0
				},
				{
					"directoryIndex" : 0,
					"id" : "Experimental::@6890427a1f51a3e7e1df",
					"jsonFile" : "target-Experimental-Release-dc6bf66df4253e53347b.json",
					"name" : "Experimental",
					"projectIndex" : 0
				},
				{
					"directoryIndex" : 0,
					"id" : "Nightly::@6890427a1f51a3e7e1df",
					"jsonFile" : "target-Nightly-Release-0a1b71b900fba136c7a2.json",
					"name" : "Nightly",
					"projectIndex" : 0
				},
				{
					"directoryIndex" : 0,
					"id" : "NightlyMemoryCheck::@6890427a1f51a3e7e1df",
					"jsonFile" : "target-NightlyMemoryCheck-Release-ee307b85b0f4c82b359b.json",
					"name" : "NightlyMemoryCheck",
					"projectIndex" : 0
				},
				{
					"directoryIndex" : 0,
					"id" : "ZERO_CHECK::@6890427a1f51a3e7e1df",
					"jsonFile" : "target-ZERO_CHECK-Release-86bbd08886eff00bd66f.json",
					"name" : "ZERO_CHECK",
					"projectIndex" : 0
				},
				{
					"directoryIndex" : 0,
					"id" : "c_bsearch::@6890427a1f51a3e7e1df",
					"jsonFile" : "target-c_bsearch-Release-cc03359db50965000fce.json",
					"name" : "c_bsearch",
					"projectIndex" : 0
				}
			]
		},
		{
			"directories" : 
			[
				{
					"build" : ".",
					"minimumCMakeVersion" : 
					{
						"string" : "3.0.0"
					},
					"projectIndex" : 0,
					"source" : ".",
					"targetIndexes" : 
					[
						0,
						1,
						2,
						3,
						4,
						5,
						6
					]
				}
			],
			"name" : "MinSizeRel",
			"projects" : 
			[
				{
					"directoryIndexes" : 
					[
						0
					],
					"name" : "c_bsearch",
					"targetIndexes" : 
					[
						0,
						1,
						2,
						3,
						4,
						5,
						6
					]
				}
			],
			"targets" : 
			[
				{
					"directoryIndex" : 0,
					"id" : "ALL_BUILD::@6890427a1f51a3e7e1df",
					"jsonFile" : "target-ALL_BUILD-MinSizeRel-5b245edb474940f28915.json",
					"name" : "ALL_BUILD",
					"projectIndex" : 0
				},
				{
					"directoryIndex" : 0,
					"id" : "Continuous::@6890427a1f51a3e7e1df",
					"jsonFile" : "target-Continuous-MinSizeRel-6937c282c87d83acf1d2.json",
					"name" : "Continuous",
					"projectIndex" : 0
				},
				{
					"directoryIndex" : 0,
					"id" : "Experimental::@6890427a1f51a3e7e1df",
					"jsonFile" : "target-Experimental-MinSizeRel-dc6bf66df4253e53347b.json",
					"name" : "Experimental",
					"projectIndex" : 0
				},
				{
					"directoryIndex" : 0,
					"id" : "Nightly::@6890427a1f51a3e7e1df",
					"jsonFile" : "target-Nightly-MinSizeRel-0a1b71b900fba136c7a2.json",
					"name" : "Nightly",
					"projectIndex" : 0
				},
				{
					"directoryIndex" : 0,
					"id" : "NightlyMemoryCheck::@6890427a1f51a3e7e1df",
					"jsonFile" : "target-NightlyMemoryCheck-MinSizeRel-ee307b85b0f4c82b359b.json",
					"name" : "NightlyMemoryCheck",
					"projectIndex" : 0
				},
				{
					"directoryIndex" : 0,
					"id" : "ZERO_CHECK::@6890427a1f51a3e7e1df",
					"jsonFile" : "target-ZERO_CHECK-MinSizeRel-86bbd08886eff00bd66f.json",
					"name" : "ZERO_CHECK",
					"projectIndex" : 0
				},
				{
					"directoryIndex" : 0,
					"id" : "c_bsearch::@6890427a1f51a3e7e1df",
					"jsonFile" : "target-c_bsearch-MinSizeRel-2d906e9fb08a5b616f18.json",
					"name" : "c_bsearch",
					"projectIndex" : 0
				}
			]
		},
		{
			"directories" : 
			[
				{
					"build" : ".",
					"minimumCMakeVersion" : 
					{
						"string" : "3.0.0"
					},
					"projectIndex" : 0,
					"source" : ".",
					"targetIndexes" : 
					[
						0,
						1,
						2,
						3,
						4,
						5,
						6
					]
				}
			],
			"name" : "RelWithDebInfo",
			"projects" : 
			[
				{
					"directoryIndexes" : 
					[
						0
					],
					"name" : "c_bsearch",
					"targetIndexes" : 
					[
						0,
						1,
						2,
						3,
						4,
						5,
						6
					]
				}
			],
			"targets" : 
			[
				{
					"directoryIndex" : 0,
					"id" : "ALL_BUILD::@6890427a1f51a3e7e1df",
					"jsonFile" : "target-ALL_BUILD-RelWithDebInfo-5b245edb474940f28915.json",
					"name" : "ALL_BUILD",
					"projectIndex" : 0
				},
				{
					"directoryIndex" : 0,
					"id" : "Continuous::@6890427a1f51a3e7e1df",
					"jsonFile" : "target-Continuous-RelWithDebInfo-6937c282c87d83acf1d2.json",
					"name" : "Continuous",
					"projectIndex" : 0
				},
				{
					"directoryIndex" : 0,
					"id" : "Experimental::@6890427a1f51a3e7e1df",
					"jsonFile" : "target-Experimental-RelWithDebInfo-dc6bf66df4253e53347b.json",
					"name" : "Experimental",
					"projectIndex" : 0
				},
				{
					"directoryIndex" : 0,
					"id" : "Nightly::@6890427a1f51a3e7e1df",
					"jsonFile" : "target-Nightly-RelWithDebInfo-0a1b71b900fba136c7a2.json",
					"name" : "Nightly",
					"projectIndex" : 0
				},
				{
					"directoryIndex" : 0,
					"id" : "NightlyMemoryCheck::@6890427a1f51a3e7e1df",
					"jsonFile" : "target-NightlyMemoryCheck-RelWithDebInfo-ee307b85b0f4c82b359b.json",
					"name" : "NightlyMemoryCheck",
					"projectIndex" : 0
				},
				{
					"directoryIndex" : 0,
					"id" : "ZERO_CHECK::@6890427a1f51a3e7e1df",
					"jsonFile" : "target-ZERO_CHECK-RelWithDebInfo-86bbd08886eff00bd66f.json",
					"name" : "ZERO_CHECK",
					"projectIndex" : 0
				},
				{
					"directoryIndex" : 0,
					"id" : "c_bsearch::@6890427a1f51a3e7e1df",
					"jsonFile" : "target-c_bsearch-RelWithDebInfo-3aa2db05bf9e8596c7b6.json",
					"name" : "c_bsearch",
					"projectIndex" : 0
				}
			]
		}
	],
	"kind" : "codemodel",
	"paths" : 
	{
		"build" : "D:/STORAGE/C++/My code/Chapter 8/8.2 - Find Element in Array/build",
		"source" : "D:/STORAGE/C++/My code/Chapter 8/8.2 - Find Element in Array"
	},
	"version" : 
	{
		"major" : 2,
		"minor" : 2
	}
}
